pytest_modifyjunit/__init__.py
pytest_modifyjunit/plugin.py
pytest_modifyjunit-1.0.dist-info/DESCRIPTION.rst
pytest_modifyjunit-1.0.dist-info/METADATA
pytest_modifyjunit-1.0.dist-info/RECORD
pytest_modifyjunit-1.0.dist-info/WHEEL
pytest_modifyjunit-1.0.dist-info/entry_points.txt
pytest_modifyjunit-1.0.dist-info/metadata.json
pytest_modifyjunit-1.0.dist-info/top_level.txt
