Metadata-Version: 2.0
Name: pytest-modifyjunit
Version: 1.0
Summary: Utility for adding additional properties to junit xml for IDM QE
Home-page: UNKNOWN
Author: Scott Poore, Niranjan M.R
Author-email: spoore@redhat.com, mrniranjan@fedoraproject.org
License: GPL
Platform: UNKNOWN
Classifier: License :: OSI Approved :: GNU General Public License v3 or later (GPLv3+)
Classifier: Operating System :: POSIX
Classifier: Framework :: Pytest
Classifier: Programming Language :: Python
Classifier: Programming Language :: Python :: 2.7
Requires-Dist: pytest (>=2.4.0)
